ystreamer/__init__.py
ystreamer/yaticker_pb2.py
ystreamer-1.1.0.dist-info/LICENSE
ystreamer-1.1.0.dist-info/METADATA
ystreamer-1.1.0.dist-info/WHEEL
ystreamer-1.1.0.dist-info/top_level.txt
ystreamer-1.1.0.dist-info/RECORD
