Metadata-Version: 2.1
Name: ystreamer
Version: 1.1.0
Summary: API to interact with Yahoo Finance Websocket API
Home-page: https://github.com/bwees/ystreamer
Author: bwees
Author-email: brandonwees@gmail.com
License: Apache 2.0
Platform: UNKNOWN
Classifier: Programming Language :: Python :: 3
Classifier: Programming Language :: Python :: 3.7
License-File: LICENSE
Requires-Dist: websocket-client
Requires-Dist: protobuf
